Metadata-Version: 1.0
Name: pypippackageexample-ed
Version: 0.0.2
Summary: paquete de prueba para una clase de Udemy
Home-page: https://github.com/edvalenzuela/py-pip-package-example
Author: Eduardo
Author-email: UNKNOWN
License: MIT
Platform: UNKNOWN
